README.txt
setup.py
Products/__init__.py
Products.atctflashpatch.egg-info/PKG-INFO
Products.atctflashpatch.egg-info/SOURCES.txt
Products.atctflashpatch.egg-info/dependency_links.txt
Products.atctflashpatch.egg-info/entry_points.txt
Products.atctflashpatch.egg-info/namespace_packages.txt
Products.atctflashpatch.egg-info/not-zip-safe
Products.atctflashpatch.egg-info/requires.txt
Products.atctflashpatch.egg-info/top_level.txt
Products/atctflashpatch/__init__.py
Products/atctflashpatch/patch.py